MANIFEST.in
account_chart_template.xml
account_types.xml
l10n_uy_wizard.xml
setup.py
taxes_code_template.xml
taxes_template.xml
./__init__.py
./__openerp__.py
i18n/es_ES.po
i18n/es_UY.po
images/config_chart_l10n_uy.jpeg
images/l10n_uy_chart.jpeg
openerp_l10n_uy.egg-info/PKG-INFO
openerp_l10n_uy.egg-info/SOURCES.txt
openerp_l10n_uy.egg-info/dependency_links.txt
openerp_l10n_uy.egg-info/requires.txt
openerp_l10n_uy.egg-info/top_level.txt
static/src/img/icon.png