Metadata-Version: 1.1
Name: openerp-l10n-uy
Version: 7.0.406
Summary: Uruguay - Chart of Accounts
Home-page: https://launchpad.net/openerp-uruguay
Author: Uruguay l10n Team & Guillem Barba
Author-email: TODO
License: AGPL-3
Platform: UNKNOWN
Classifier: Development Status :: 5 - Production/Stable
Classifier: Environment :: Plugins
Classifier: Intended Audience :: Developers
Classifier: License :: OSI Approved :: GNU Affero General Public License v3
Classifier: Natural Language :: English
Classifier: Programming Language :: Python :: 2.7
Classifier: Programming Language :: Python :: Implementation :: CPython
